{
  "Ticker": "ADBE",
  "Company": "Adobe Inc.",
  "Market": "NASDAQ",
  "Price at Analysis": "195.16",
  "Category": "C",
  "Verdict": "WATCH★★★★",
  "Stars": "4",
  "Moat": "B+",
  "Quality": "A-",
  "Val": "A",
  "Mgmt": "B",
  "AI Overlay": "🟢 WIDENER",
  "AI Score": "58",
  "Phase": "3",
  "Flywheel": "Forming",
  "Conditions Met": "0",
  "Horizon": "5-7yr",
  "Base IV": "~$353",
  "MoS Entry Zone": "$220–240",
  "Thesis": "World-class creative/document SaaS; 88% GM, $10B+ FCF, $25B ARR; priced at 9x fwd PE on AI existential fears; moat intact for enterprise; CEO transition the key near-term risk",
  "Report File": "ADBE_qv_report.html",
  "Last Analysis Date": "April 14, 2026"
}