{
  "Ticker": "FTNT",
  "Company": "Fortinet Inc",
  "Market": "NASDAQ",
  "Price at Analysis": "144.73",
  "Category": "C",
  "Verdict": "WATCH★★★★",
  "Stars": "4",
  "Moat": "B+",
  "Quality": "A-",
  "Val": "C+",
  "Mgmt": "A-",
  "AI Overlay": "🟢 WIDENER",
  "AI Score": "72",
  "Phase": "3",
  "Flywheel": "Forming",
  "Conditions Met": "3",
  "Horizon": "5-7yr",
  "Base IV": "$77–84",
  "MoS Entry Zone": "$58–65",
  "Thesis": "FortiASIC moat + forming AI flywheel (5.6M sensors); price near base IV — wait for 30% MoS entry at $58–65",
  "Report File": "FTNT_qv_report.html",
  "Last Analysis Date": "April 26, 2026"
}